{"directed": false, "multigraph": false, "graph": {"name": "01-spring-layout", "graphtitle": "Zachary", "graphdesc": "Karateclub toy network"}, "nodes": [{"club": "Mr. Hi", "annotation": ["Node: 0", "Club: Mr. Hi"], "pos": [0.06287198998515463, 0.25783949576181114, 0.3343541170106573], "nodecolor": "#c90823", "id": 0}, {"club": "Mr. Hi", "annotation": ["Node: 1", "Club: Mr. Hi"], "pos": [0.05968274910296169, 0.015161731833686324, 0.302800429523431], "nodecolor": "#fc6330", "id": 1}, {"club": "Mr. Hi", "annotation": ["Node: 2", "Club: Mr. Hi"], "pos": [0.09517252627674115, 0.012776419437737396, 0.0676403916987025], "nodecolor": "#f43d25", "id": 2}, {"club": "Mr. Hi", "annotation": ["Node: 3", "Club: Mr. Hi"], "pos": [0.23785819627696433, 0.025945309638106786, 0.3788299894312418], "nodecolor": "#fd8c3c", "id": 3}, {"club": "Mr. Hi", "annotation": ["Node: 4", "Club: Mr. Hi"], "pos": [0.13533109550543204, 0.5852353111958293, 0.5232292388373819], "nodecolor": "#fed976", "id": 4}, {"club": "Mr. Hi", "annotation": ["Node: 5", "Club: Mr. Hi"], "pos": [-0.05916243101917884, 0.7003108405910818, 0.4849486867908506], "nodecolor": "#febf5a", "id": 5}, {"club": "Mr. Hi", "annotation": ["Node: 6", "Club: Mr. Hi"], "pos": [0.029372076278456904, 0.7232839395512181, 0.39866411798799545], "nodecolor": "#febf5a", "id": 6}, {"club": "Mr. Hi", "annotation": ["Node: 7", "Club: Mr. Hi"], "pos": [0.2540158494559034, 0.11344705002901444, 0.25481206146574187], "nodecolor": "#febf5a", "id": 7}, {"club": "Mr. Hi", "annotation": ["Node: 8", "Club: Mr. Hi"], "pos": [0.01763432487827819, -0.10524983309451728, -0.07064237377904177], "nodecolor": "#fea647", "id": 8}, {"club": "Officer", "annotation": ["Node: 9", "Club: Officer"], "pos": [0.33287998334016344, -0.42053845723958516, -0.1345178863184342], "nodecolor": "#ffe793", "id": 9}, {"club": "Mr. Hi", "annotation": ["Node: 10", "Club: Mr. Hi"], "pos": [0.0031075537517848773, 0.6075945332829489, 0.647806244980027], "nodecolor": "#fed976", "id": 10}, {"club": "Mr. Hi", "annotation": ["Node: 11", "Club: Mr. Hi"], "pos": [0.35005253827649185, 0.43859129057430657, 0.5862298855637015], "nodecolor": "#fff3af", "id": 11}, {"club": "Mr. Hi", "annotation": ["Node: 12", "Club: Mr. Hi"], "pos": [0.42768206498826467, 0.03953760223113425, 0.6471014137869191], "nodecolor": "#ffe793", "id": 12}, {"club": "Mr. Hi", "annotation": ["Node: 13", "Club: Mr. Hi"], "pos": [0.07927054574031708, -0.07346098650622683, 0.1666917095400542], "nodecolor": "#fea647", "id": 13}, {"club": "Officer", "annotation": ["Node: 14", "Club: Officer"], "pos": [0.164049574385915, -0.35484119638184886, -0.6117751415175425], "nodecolor": "#ffe793", "id": 14}, {"club": "Officer", "annotation": ["Node: 15", "Club: Officer"], "pos": [0.09944869208308482, -0.48765203842523674, -0.4281419354165289], "nodecolor": "#ffe793", "id": 15}, {"club": "Mr. Hi", "annotation": ["Node: 16", "Club: Mr. Hi"], "pos": [-0.06484135292279267, 1.0, 0.49179409966890797], "nodecolor": "#ffe793", "id": 16}, {"club": "Mr. Hi", "annotation": ["Node: 17", "Club: Mr. Hi"], "pos": [-0.1554415153546044, 0.21475141861840952, 0.6770899513004021], "nodecolor": "#ffe793", "id": 17}, {"club": "Officer", "annotation": ["Node: 18", "Club: Officer"], "pos": [0.049857230211191386, -0.7092143030599523, -0.454024021132266], "nodecolor": "#ffe793", "id": 18}, {"club": "Mr. Hi", "annotation": ["Node: 19", "Club: Mr. Hi"], "pos": [-0.1954873626427281, -0.030522157781208134, 0.27576670283381793], "nodecolor": "#fed976", "id": 19}, {"club": "Officer", "annotation": ["Node: 20", "Club: Officer"], "pos": [-0.02540762737504319, -0.37046812801235424, -0.7410123027972806], "nodecolor": "#ffe793", "id": 20}, {"club": "Mr. Hi", "annotation": ["Node: 21", "Club: Mr. Hi"], "pos": [0.0617778722979455, 0.07341960603112657, 0.676352000990051], "nodecolor": "#ffe793", "id": 21}, {"club": "Officer", "annotation": ["Node: 22", "Club: Officer"], "pos": [-0.1562484207925816, -0.5967300855071993, -0.34556285425302313], "nodecolor": "#ffe793", "id": 22}, {"club": "Officer", "annotation": ["Node: 23", "Club: Officer"], "pos": [-0.2145970742858923, -0.15971265239501048, -0.4788956866561765], "nodecolor": "#fea647", "id": 23}, {"club": "Officer", "annotation": ["Node: 24", "Club: Officer"], "pos": [-0.419943205967107, 0.16085549921671247, -0.4644282720744195], "nodecolor": "#fed976", "id": 24}, {"club": "Officer", "annotation": ["Node: 25", "Club: Officer"], "pos": [-0.2426775824190525, 0.07786040003749345, -0.5105022901219866], "nodecolor": "#fed976", "id": 25}, {"club": "Officer", "annotation": ["Node: 26", "Club: Officer"], "pos": [-0.3791062675564522, -0.5469424001669656, -0.5532297868142767], "nodecolor": "#ffe793", "id": 26}, {"club": "Officer", "annotation": ["Node: 27", "Club: Officer"], "pos": [-0.24702987498545897, -0.04918131438584465, -0.29846946411019243], "nodecolor": "#febf5a", "id": 27}, {"club": "Officer", "annotation": ["Node: 28", "Club: Officer"], "pos": [0.16373564631085755, 0.04674292058888297, -0.29817921039082845], "nodecolor": "#fed976", "id": 28}, {"club": "Officer", "annotation": ["Node: 29", "Club: Officer"], "pos": [-0.25809766886385743, -0.3887514003316666, -0.5286441298131895], "nodecolor": "#febf5a", "id": 29}, {"club": "Officer", "annotation": ["Node: 30", "Club: Officer"], "pos": [-0.01734425032913111, -0.286693351248353, -0.044315616406670796], "nodecolor": "#febf5a", "id": 30}, {"club": "Officer", "annotation": ["Node: 31", "Club: Officer"], "pos": [-0.10998094981841922, 0.03887482081343054, -0.2900193416645003], "nodecolor": "#fd8c3c", "id": 31}, {"club": "Officer", "annotation": ["Node: 32", "Club: Officer"], "pos": [-0.03527716450367692, -0.2748764076870153, -0.3793435733993844], "nodecolor": "#e2191c", "id": 32}, {"club": "Officer", "annotation": ["Node: 33", "Club: Officer"], "pos": [-0.04315776030993224, -0.27739347720994545, -0.2824071547441398], "nodecolor": "#a80026", "id": 33}], "links": [{"weight": 4, "linkcolor": "#909090", "source": 0, "target": 1}, {"weight": 5, "linkcolor": "#909090", "source": 0, "target": 2}, {"weight": 3, "linkcolor": "#909090", "source": 0, "target": 3}, {"weight": 3, "linkcolor": "#909090", "source": 0, "target": 4}, {"weight": 3, "linkcolor": "#909090", "source": 0, "target": 5}, {"weight": 3, "linkcolor": "#909090", "source": 0, "target": 6}, {"weight": 2, "linkcolor": "#909090", "source": 0, "target": 7}, {"weight": 2, "linkcolor": "#909090", "source": 0, "target": 8}, {"weight": 2, "linkcolor": "#909090", "source": 0, "target": 10}, {"weight": 3, "linkcolor": "#909090", "source": 0, "target": 11}, {"weight": 1, "linkcolor": "#909090", "source": 0, "target": 12}, {"weight": 3, "linkcolor": "#909090", "source": 0, "target": 13}, {"weight": 2, "linkcolor": "#909090", "source": 0, "target": 17}, {"weight": 2, "linkcolor": "#909090", "source": 0, "target": 19}, {"weight": 2, "linkcolor": "#909090", "source": 0, "target": 21}, {"weight": 2, "linkcolor": "#909090", "source": 0, "target": 31}, {"weight": 6, "linkcolor": "#909090", "source": 1, "target": 2}, {"weight": 3, "linkcolor": "#909090", "source": 1, "target": 3}, {"weight": 4, "linkcolor": "#909090", "source": 1, "target": 7}, {"weight": 5, "linkcolor": "#909090", "source": 1, "target": 13}, {"weight": 1, "linkcolor": "#909090", "source": 1, "target": 17}, {"weight": 2, "linkcolor": "#909090", "source": 1, "target": 19}, {"weight": 2, "linkcolor": "#909090", "source": 1, "target": 21}, {"weight": 2, "linkcolor": "#909090", "source": 1, "target": 30}, {"weight": 3, "linkcolor": "#909090", "source": 2, "target": 3}, {"weight": 4, "linkcolor": "#909090", "source": 2, "target": 7}, {"weight": 5, "linkcolor": "#909090", "source": 2, "target": 8}, {"weight": 1, "linkcolor": "#909090", "source": 2, "target": 9}, {"weight": 3, "linkcolor": "#909090", "source": 2, "target": 13}, {"weight": 2, "linkcolor": "#909090", "source": 2, "target": 27}, {"weight": 2, "linkcolor": "#909090", "source": 2, "target": 28}, {"weight": 2, "linkcolor": "#909090", "source": 2, "target": 32}, {"weight": 3, "linkcolor": "#909090", "source": 3, "target": 7}, {"weight": 3, "linkcolor": "#909090", "source": 3, "target": 12}, {"weight": 3, "linkcolor": "#909090", "source": 3, "target": 13}, {"weight": 2, "linkcolor": "#909090", "source": 4, "target": 6}, {"weight": 3, "linkcolor": "#909090", "source": 4, "target": 10}, {"weight": 5, "linkcolor": "#909090", "source": 5, "target": 6}, {"weight": 3, "linkcolor": "#909090", "source": 5, "target": 10}, {"weight": 3, "linkcolor": "#909090", "source": 5, "target": 16}, {"weight": 3, "linkcolor": "#909090", "source": 6, "target": 16}, {"weight": 3, "linkcolor": "#909090", "source": 8, "target": 30}, {"weight": 3, "linkcolor": "#909090", "source": 8, "target": 32}, {"weight": 4, "linkcolor": "#909090", "source": 8, "target": 33}, {"weight": 2, "linkcolor": "#909090", "source": 9, "target": 33}, {"weight": 3, "linkcolor": "#909090", "source": 13, "target": 33}, {"weight": 3, "linkcolor": "#909090", "source": 14, "target": 32}, {"weight": 2, "linkcolor": "#909090", "source": 14, "target": 33}, {"weight": 3, "linkcolor": "#909090", "source": 15, "target": 32}, {"weight": 4, "linkcolor": "#909090", "source": 15, "target": 33}, {"weight": 1, "linkcolor": "#909090", "source": 18, "target": 32}, {"weight": 2, "linkcolor": "#909090", "source": 18, "target": 33}, {"weight": 1, "linkcolor": "#909090", "source": 19, "target": 33}, {"weight": 3, "linkcolor": "#909090", "source": 20, "target": 32}, {"weight": 1, "linkcolor": "#909090", "source": 20, "target": 33}, {"weight": 2, "linkcolor": "#909090", "source": 22, "target": 32}, {"weight": 3, "linkcolor": "#909090", "source": 22, "target": 33}, {"weight": 5, "linkcolor": "#909090", "source": 23, "target": 25}, {"weight": 4, "linkcolor": "#909090", "source": 23, "target": 27}, {"weight": 3, "linkcolor": "#909090", "source": 23, "target": 29}, {"weight": 5, "linkcolor": "#909090", "source": 23, "target": 32}, {"weight": 4, "linkcolor": "#909090", "source": 23, "target": 33}, {"weight": 2, "linkcolor": "#909090", "source": 24, "target": 25}, {"weight": 3, "linkcolor": "#909090", "source": 24, "target": 27}, {"weight": 2, "linkcolor": "#909090", "source": 24, "target": 31}, {"weight": 7, "linkcolor": "#909090", "source": 25, "target": 31}, {"weight": 4, "linkcolor": "#909090", "source": 26, "target": 29}, {"weight": 2, "linkcolor": "#909090", "source": 26, "target": 33}, {"weight": 4, "linkcolor": "#909090", "source": 27, "target": 33}, {"weight": 2, "linkcolor": "#909090", "source": 28, "target": 31}, {"weight": 2, "linkcolor": "#909090", "source": 28, "target": 33}, {"weight": 4, "linkcolor": "#909090", "source": 29, "target": 32}, {"weight": 2, "linkcolor": "#909090", "source": 29, "target": 33}, {"weight": 3, "linkcolor": "#909090", "source": 30, "target": 32}, {"weight": 3, "linkcolor": "#909090", "source": 30, "target": 33}, {"weight": 4, "linkcolor": "#909090", "source": 31, "target": 32}, {"weight": 4, "linkcolor": "#909090", "source": 31, "target": 33}, {"weight": 5, "linkcolor": "#909090", "source": 32, "target": 33}]}