{
    "directed": false,
    "multigraph": false,
    "graph": {
        "name": "layout3-spring",
        "projectname": "MYPROJECT_1",
        "info": "A toy graph for testing purposes. Number of nodes: 30, Links: 176.",
        "scene": "layout3-spring"
    },
    "nodes": [
        {
            "pos": [
                -0.2830253269646975,
                0.38379459395228444,
                0.42237732065879874
            ],
            "annotation": {
                "annot1": [
                    "zeta",
                    "gamma",
                    "alpha"
                ],
                "annot2": [
                    "alpha",
                    "zeta"
                ],
                "annot3": [
                    "beta",
                    "lambda",
                    "theta"
                ]
            },
            "nodecolor": "#0000ffaa",
            "id": 0
        },
        {
            "pos": [
                0.8617970814857111,
                -0.42732485910673595,
                -0.666160160312233
            ],
            "annotation": {
                "annot1": [
                    "gamma",
                    "alpha",
                    "nu",
                    "mu"
                ],
                "annot2": [
                    "lambda"
                ],
                "annot3": [
                    "delta",
                    "beta"
                ]
            },
            "nodecolor": "#0000ffaa",
            "id": 1
        },
        {
            "pos": [
                0.45814706579133324,
                -0.42605809962824487,
                -0.5706145703013753
            ],
            "annotation": {
                "annot1": [
                    "delta",
                    "beta",
                    "lambda"
                ],
                "annot2": [
                    "gamma",
                    "nu"
                ],
                "annot3": [
                    "gamma",
                    "zeta",
                    "beta"
                ]
            },
            "nodecolor": "#0000ffaa",
            "id": 2
        },
        {
            "pos": [
                0.2319072840297074,
                0.6223804517602457,
                0.2894376829511398
            ],
            "annotation": {
                "annot1": [
                    "epsilon",
                    "delta",
                    "alpha",
                    "nu"
                ],
                "annot2": [
                    "beta"
                ],
                "annot3": [
                    "lambda",
                    "delta",
                    "epsilon"
                ]
            },
            "nodecolor": "#0000ffaa",
            "id": 3
        },
        {
            "pos": [
                0.296960203840832,
                -0.2104452497296516,
                -0.2053155440732281
            ],
            "annotation": {
                "annot1": [
                    "zeta",
                    "alpha",
                    "gamma",
                    "lambda"
                ],
                "annot2": [
                    "delta"
                ],
                "annot3": [
                    "theta",
                    "gamma"
                ]
            },
            "nodecolor": "#0000ffaa",
            "id": 4
        },
        {
            "pos": [
                -0.2043280100305997,
                -0.37498229733388316,
                -0.15171620401669214
            ],
            "annotation": {
                "annot1": [
                    "delta",
                    "mu",
                    "lambda",
                    "theta"
                ],
                "annot2": [
                    "nu"
                ],
                "annot3": [
                    "alpha",
                    "gamma",
                    "lambda"
                ]
            },
            "nodecolor": "#0000ffaa",
            "id": 5
        },
        {
            "pos": [
                0.35824684450319777,
                0.3230325433651831,
                -0.16147488521739115
            ],
            "annotation": {
                "annot1": [
                    "gamma",
                    "nu",
                    "epsilon",
                    "delta"
                ],
                "annot2": [
                    "theta",
                    "lambda"
                ],
                "annot3": [
                    "lambda",
                    "beta",
                    "gamma"
                ]
            },
            "nodecolor": "#0000ffaa",
            "id": 6
        },
        {
            "pos": [
                0.8915840546555064,
                -0.1292888255713048,
                -0.35234273495107876
            ],
            "annotation": {
                "annot1": [
                    "mu",
                    "gamma",
                    "alpha",
                    "delta"
                ],
                "annot2": [
                    "alpha"
                ],
                "annot3": [
                    "delta",
                    "epsilon",
                    "nu"
                ]
            },
            "nodecolor": "#0000ffaa",
            "id": 7
        },
        {
            "pos": [
                -0.5346652922652069,
                0.6252060651331971,
                0.6427812653959407
            ],
            "annotation": {
                "annot1": [
                    "alpha",
                    "nu",
                    "theta"
                ],
                "annot2": [
                    "beta",
                    "epsilon"
                ],
                "annot3": [
                    "gamma",
                    "beta"
                ]
            },
            "nodecolor": "#0000ffaa",
            "id": 8
        },
        {
            "pos": [
                0.7950493115896207,
                -0.015874411845884596,
                -0.5779084712126057
            ],
            "annotation": {
                "annot1": [
                    "alpha",
                    "gamma",
                    "mu",
                    "delta"
                ],
                "annot2": [
                    "beta",
                    "epsilon"
                ],
                "annot3": [
                    "zeta",
                    "lambda",
                    "nu"
                ]
            },
            "nodecolor": "#0000ffaa",
            "id": 9
        },
        {
            "pos": [
                -0.8227855991668093,
                -0.34208605124137587,
                0.34421603776036686
            ],
            "annotation": {
                "annot1": [
                    "nu",
                    "alpha",
                    "lambda"
                ],
                "annot2": [
                    "gamma"
                ],
                "annot3": [
                    "alpha",
                    "mu"
                ]
            },
            "nodecolor": "#0000ffaa",
            "id": 10
        },
        {
            "pos": [
                0.3207115947930839,
                -0.47365788279970683,
                -0.2970121173215968
            ],
            "annotation": {
                "annot1": [
                    "delta",
                    "lambda",
                    "nu",
                    "zeta"
                ],
                "annot2": [
                    "lambda"
                ],
                "annot3": [
                    "nu",
                    "epsilon"
                ]
            },
            "nodecolor": "#0000ffaa",
            "id": 11
        },
        {
            "pos": [
                0.11661607342486023,
                -0.003085463364317588,
                -0.06871064443051235
            ],
            "annotation": {
                "annot1": [
                    "epsilon",
                    "mu",
                    "nu",
                    "zeta"
                ],
                "annot2": [
                    "gamma",
                    "lambda"
                ],
                "annot3": [
                    "theta",
                    "alpha",
                    "mu"
                ]
            },
            "nodecolor": "#0000ffaa",
            "id": 12
        },
        {
            "pos": [
                0.3772206107307965,
                0.2748412662902833,
                0.04404958873508721
            ],
            "annotation": {
                "annot1": [
                    "alpha",
                    "epsilon",
                    "nu"
                ],
                "annot2": [
                    "lambda",
                    "mu"
                ],
                "annot3": [
                    "beta",
                    "gamma",
                    "epsilon"
                ]
            },
            "nodecolor": "#0000ffaa",
            "id": 13
        },
        {
            "pos": [
                -0.44930635144384357,
                -0.3545158186909292,
                -0.05649412980899596
            ],
            "annotation": {
                "annot1": [
                    "delta",
                    "epsilon",
                    "zeta"
                ],
                "annot2": [
                    "alpha",
                    "delta"
                ],
                "annot3": [
                    "beta",
                    "lambda",
                    "mu"
                ]
            },
            "nodecolor": "#0000ffaa",
            "id": 14
        },
        {
            "pos": [
                0.33075537389208204,
                -0.1720323809410886,
                -0.5054332542012088
            ],
            "annotation": {
                "annot1": [
                    "nu",
                    "epsilon",
                    "mu",
                    "gamma"
                ],
                "annot2": [
                    "delta"
                ],
                "annot3": [
                    "lambda",
                    "epsilon"
                ]
            },
            "nodecolor": "#0000ffaa",
            "id": 15
        },
        {
            "pos": [
                -0.21054668958461747,
                0.24270458878405898,
                0.18497343534393423
            ],
            "annotation": {
                "annot1": [
                    "delta",
                    "gamma",
                    "theta"
                ],
                "annot2": [
                    "gamma",
                    "lambda"
                ],
                "annot3": [
                    "lambda",
                    "zeta"
                ]
            },
            "nodecolor": "#0000ffaa",
            "id": 16
        },
        {
            "pos": [
                0.5642416316270371,
                0.029189387628753234,
                -0.5240108933349427
            ],
            "annotation": {
                "annot1": [
                    "beta",
                    "gamma",
                    "mu"
                ],
                "annot2": [
                    "theta"
                ],
                "annot3": [
                    "nu",
                    "gamma",
                    "delta"
                ]
            },
            "nodecolor": "#0000ffaa",
            "id": 17
        },
        {
            "pos": [
                -0.3037089357496157,
                -0.9925820085336413,
                -0.256784065802771
            ],
            "annotation": {
                "annot1": [
                    "theta",
                    "alpha",
                    "beta",
                    "mu"
                ],
                "annot2": [
                    "alpha"
                ],
                "annot3": [
                    "beta",
                    "delta"
                ]
            },
            "nodecolor": "#0000ffaa",
            "id": 18
        },
        {
            "pos": [
                -0.07126666165391252,
                0.6603775805524169,
                0.4928313194855782
            ],
            "annotation": {
                "annot1": [
                    "delta",
                    "zeta",
                    "gamma"
                ],
                "annot2": [
                    "alpha",
                    "delta"
                ],
                "annot3": [
                    "mu",
                    "lambda",
                    "theta"
                ]
            },
            "nodecolor": "#0000ffaa",
            "id": 19
        },
        {
            "pos": [
                -0.1628972572610522,
                0.0857160512722172,
                0.18016763157012938
            ],
            "annotation": {
                "annot1": [
                    "nu",
                    "epsilon",
                    "mu",
                    "delta"
                ],
                "annot2": [
                    "beta"
                ],
                "annot3": [
                    "lambda",
                    "gamma",
                    "delta"
                ]
            },
            "nodecolor": "#0000ffaa",
            "id": 20
        },
        {
            "pos": [
                0.03331954117004902,
                -0.09599582143914673,
                -0.2345335703652656
            ],
            "annotation": {
                "annot1": [
                    "alpha",
                    "beta",
                    "lambda"
                ],
                "annot2": [
                    "delta",
                    "alpha"
                ],
                "annot3": [
                    "lambda",
                    "zeta"
                ]
            },
            "nodecolor": "#0000ffaa",
            "id": 21
        },
        {
            "pos": [
                -0.5501317391406001,
                0.39039464668581986,
                0.8071349978235334
            ],
            "annotation": {
                "annot1": [
                    "lambda",
                    "epsilon",
                    "nu",
                    "theta"
                ],
                "annot2": [
                    "lambda"
                ],
                "annot3": [
                    "beta",
                    "mu"
                ]
            },
            "nodecolor": "#0000ffaa",
            "id": 22
        },
        {
            "pos": [
                -0.04297272309548973,
                -0.6212128618177053,
                -0.41443462924498947
            ],
            "annotation": {
                "annot1": [
                    "beta",
                    "gamma",
                    "delta",
                    "epsilon"
                ],
                "annot2": [
                    "lambda"
                ],
                "annot3": [
                    "gamma",
                    "epsilon",
                    "alpha"
                ]
            },
            "nodecolor": "#0000ffaa",
            "id": 23
        },
        {
            "pos": [
                0.6813965231482086,
                -0.15441012890540473,
                -0.24528207291610782
            ],
            "annotation": {
                "annot1": [
                    "alpha",
                    "epsilon",
                    "gamma",
                    "theta"
                ],
                "annot2": [
                    "beta",
                    "lambda"
                ],
                "annot3": [
                    "epsilon",
                    "alpha"
                ]
            },
            "nodecolor": "#0000ffaa",
            "id": 24
        },
        {
            "pos": [
                -0.1149989656515131,
                0.6816776172262536,
                0.1666067351009184
            ],
            "annotation": {
                "annot1": [
                    "zeta",
                    "delta",
                    "alpha"
                ],
                "annot2": [
                    "delta",
                    "mu"
                ],
                "annot3": [
                    "epsilon",
                    "lambda",
                    "beta"
                ]
            },
            "nodecolor": "#0000ffaa",
            "id": 25
        },
        {
            "pos": [
                -0.6567131527603027,
                0.033930670374064394,
                0.41067077274966723
            ],
            "annotation": {
                "annot1": [
                    "beta",
                    "zeta",
                    "delta"
                ],
                "annot2": [
                    "alpha",
                    "zeta"
                ],
                "annot3": [
                    "nu",
                    "gamma"
                ]
            },
            "nodecolor": "#0000ffaa",
            "id": 26
        },
        {
            "pos": [
                -0.23907844702473185,
                -0.45853358998077776,
                0.09974821562565701
            ],
            "annotation": {
                "annot1": [
                    "lambda",
                    "beta",
                    "delta",
                    "alpha"
                ],
                "annot2": [
                    "mu"
                ],
                "annot3": [
                    "lambda",
                    "theta"
                ]
            },
            "nodecolor": "#0000ffaa",
            "id": 27
        },
        {
            "pos": [
                -0.671528042889026,
                0.599173263881459,
                0.43957846430563297
            ],
            "annotation": {
                "annot1": [
                    "theta",
                    "gamma",
                    "lambda",
                    "alpha"
                ],
                "annot2": [
                    "delta"
                ],
                "annot3": [
                    "gamma",
                    "nu"
                ]
            },
            "nodecolor": "#0000ffaa",
            "id": 28
        },
        {
            "pos": [
                -1.0,
                0.2996670240235693,
                0.7636544800046217
            ],
            "annotation": {
                "annot1": [
                    "lambda",
                    "delta",
                    "zeta",
                    "theta"
                ],
                "annot2": [
                    "lambda",
                    "epsilon"
                ],
                "annot3": [
                    "lambda",
                    "delta"
                ]
            },
            "nodecolor": "#0000ffaa",
            "id": 29
        }
    ],
    "links": [
        {
            "linkcolor": "#0080ffaa",
            "source": 0,
            "target": 3
        },
        {
            "linkcolor": "#0080ffaa",
            "source": 0,
            "target": 8
        },
        {
            "linkcolor": "#0080ffaa",
            "source": 0,
            "target": 12
        },
        {
            "linkcolor": "#0080ffaa",
            "source": 0,
            "target": 13
        },
        {
            "linkcolor": "#0080ffaa",
            "source": 0,
            "target": 16
        },
        {
            "linkcolor": "#0080ffaa",
            "source": 0,
            "target": 19
        },
        {
            "linkcolor": "#0080ffaa",
            "source": 0,
            "target": 20
        },
        {
            "linkcolor": "#0080ffaa",
            "source": 0,
            "target": 21
        },
        {
            "linkcolor": "#0080ffaa",
            "source": 0,
            "target": 22
        },
        {
            "linkcolor": "#0080ffaa",
            "source": 0,
            "target": 25
        },
        {
            "linkcolor": "#0080ffaa",
            "source": 0,
            "target": 26
        },
        {
            "linkcolor": "#0080ffaa",
            "source": 0,
            "target": 28
        },
        {
            "linkcolor": "#0080ffaa",
            "source": 0,
            "target": 29
        },
        {
            "linkcolor": "#0080ffaa",
            "source": 1,
            "target": 2
        },
        {
            "linkcolor": "#0080ffaa",
            "source": 1,
            "target": 4
        },
        {
            "linkcolor": "#0080ffaa",
            "source": 1,
            "target": 7
        },
        {
            "linkcolor": "#0080ffaa",
            "source": 1,
            "target": 9
        },
        {
            "linkcolor": "#0080ffaa",
            "source": 1,
            "target": 11
        },
        {
            "linkcolor": "#0080ffaa",
            "source": 1,
            "target": 15
        },
        {
            "linkcolor": "#0080ffaa",
            "source": 1,
            "target": 17
        },
        {
            "linkcolor": "#0080ffaa",
            "source": 1,
            "target": 24
        },
        {
            "linkcolor": "#0080ffaa",
            "source": 2,
            "target": 4
        },
        {
            "linkcolor": "#0080ffaa",
            "source": 2,
            "target": 5
        },
        {
            "linkcolor": "#0080ffaa",
            "source": 2,
            "target": 7
        },
        {
            "linkcolor": "#0080ffaa",
            "source": 2,
            "target": 9
        },
        {
            "linkcolor": "#0080ffaa",
            "source": 2,
            "target": 11
        },
        {
            "linkcolor": "#0080ffaa",
            "source": 2,
            "target": 12
        },
        {
            "linkcolor": "#0080ffaa",
            "source": 2,
            "target": 15
        },
        {
            "linkcolor": "#0080ffaa",
            "source": 2,
            "target": 17
        },
        {
            "linkcolor": "#0080ffaa",
            "source": 2,
            "target": 21
        },
        {
            "linkcolor": "#0080ffaa",
            "source": 2,
            "target": 23
        },
        {
            "linkcolor": "#0080ffaa",
            "source": 2,
            "target": 24
        },
        {
            "linkcolor": "#0080ffaa",
            "source": 3,
            "target": 6
        },
        {
            "linkcolor": "#0080ffaa",
            "source": 3,
            "target": 12
        },
        {
            "linkcolor": "#0080ffaa",
            "source": 3,
            "target": 13
        },
        {
            "linkcolor": "#0080ffaa",
            "source": 3,
            "target": 16
        },
        {
            "linkcolor": "#0080ffaa",
            "source": 3,
            "target": 19
        },
        {
            "linkcolor": "#0080ffaa",
            "source": 3,
            "target": 20
        },
        {
            "linkcolor": "#0080ffaa",
            "source": 3,
            "target": 25
        },
        {
            "linkcolor": "#0080ffaa",
            "source": 4,
            "target": 5
        },
        {
            "linkcolor": "#0080ffaa",
            "source": 4,
            "target": 6
        },
        {
            "linkcolor": "#0080ffaa",
            "source": 4,
            "target": 7
        },
        {
            "linkcolor": "#0080ffaa",
            "source": 4,
            "target": 9
        },
        {
            "linkcolor": "#0080ffaa",
            "source": 4,
            "target": 11
        },
        {
            "linkcolor": "#0080ffaa",
            "source": 4,
            "target": 12
        },
        {
            "linkcolor": "#0080ffaa",
            "source": 4,
            "target": 13
        },
        {
            "linkcolor": "#0080ffaa",
            "source": 4,
            "target": 14
        },
        {
            "linkcolor": "#0080ffaa",
            "source": 4,
            "target": 15
        },
        {
            "linkcolor": "#0080ffaa",
            "source": 4,
            "target": 16
        },
        {
            "linkcolor": "#0080ffaa",
            "source": 4,
            "target": 17
        },
        {
            "linkcolor": "#0080ffaa",
            "source": 4,
            "target": 20
        },
        {
            "linkcolor": "#0080ffaa",
            "source": 4,
            "target": 21
        },
        {
            "linkcolor": "#0080ffaa",
            "source": 4,
            "target": 23
        },
        {
            "linkcolor": "#0080ffaa",
            "source": 4,
            "target": 24
        },
        {
            "linkcolor": "#0080ffaa",
            "source": 4,
            "target": 27
        },
        {
            "linkcolor": "#0080ffaa",
            "source": 5,
            "target": 10
        },
        {
            "linkcolor": "#0080ffaa",
            "source": 5,
            "target": 11
        },
        {
            "linkcolor": "#0080ffaa",
            "source": 5,
            "target": 12
        },
        {
            "linkcolor": "#0080ffaa",
            "source": 5,
            "target": 14
        },
        {
            "linkcolor": "#0080ffaa",
            "source": 5,
            "target": 15
        },
        {
            "linkcolor": "#0080ffaa",
            "source": 5,
            "target": 16
        },
        {
            "linkcolor": "#0080ffaa",
            "source": 5,
            "target": 18
        },
        {
            "linkcolor": "#0080ffaa",
            "source": 5,
            "target": 20
        },
        {
            "linkcolor": "#0080ffaa",
            "source": 5,
            "target": 21
        },
        {
            "linkcolor": "#0080ffaa",
            "source": 5,
            "target": 23
        },
        {
            "linkcolor": "#0080ffaa",
            "source": 5,
            "target": 26
        },
        {
            "linkcolor": "#0080ffaa",
            "source": 5,
            "target": 27
        },
        {
            "linkcolor": "#0080ffaa",
            "source": 6,
            "target": 7
        },
        {
            "linkcolor": "#0080ffaa",
            "source": 6,
            "target": 9
        },
        {
            "linkcolor": "#0080ffaa",
            "source": 6,
            "target": 12
        },
        {
            "linkcolor": "#0080ffaa",
            "source": 6,
            "target": 13
        },
        {
            "linkcolor": "#0080ffaa",
            "source": 6,
            "target": 15
        },
        {
            "linkcolor": "#0080ffaa",
            "source": 6,
            "target": 16
        },
        {
            "linkcolor": "#0080ffaa",
            "source": 6,
            "target": 17
        },
        {
            "linkcolor": "#0080ffaa",
            "source": 6,
            "target": 19
        },
        {
            "linkcolor": "#0080ffaa",
            "source": 6,
            "target": 20
        },
        {
            "linkcolor": "#0080ffaa",
            "source": 6,
            "target": 21
        },
        {
            "linkcolor": "#0080ffaa",
            "source": 6,
            "target": 24
        },
        {
            "linkcolor": "#0080ffaa",
            "source": 6,
            "target": 25
        },
        {
            "linkcolor": "#0080ffaa",
            "source": 7,
            "target": 9
        },
        {
            "linkcolor": "#0080ffaa",
            "source": 7,
            "target": 11
        },
        {
            "linkcolor": "#0080ffaa",
            "source": 7,
            "target": 13
        },
        {
            "linkcolor": "#0080ffaa",
            "source": 7,
            "target": 15
        },
        {
            "linkcolor": "#0080ffaa",
            "source": 7,
            "target": 17
        },
        {
            "linkcolor": "#0080ffaa",
            "source": 7,
            "target": 24
        },
        {
            "linkcolor": "#0080ffaa",
            "source": 8,
            "target": 16
        },
        {
            "linkcolor": "#0080ffaa",
            "source": 8,
            "target": 19
        },
        {
            "linkcolor": "#0080ffaa",
            "source": 8,
            "target": 20
        },
        {
            "linkcolor": "#0080ffaa",
            "source": 8,
            "target": 22
        },
        {
            "linkcolor": "#0080ffaa",
            "source": 8,
            "target": 25
        },
        {
            "linkcolor": "#0080ffaa",
            "source": 8,
            "target": 26
        },
        {
            "linkcolor": "#0080ffaa",
            "source": 8,
            "target": 28
        },
        {
            "linkcolor": "#0080ffaa",
            "source": 8,
            "target": 29
        },
        {
            "linkcolor": "#0080ffaa",
            "source": 9,
            "target": 11
        },
        {
            "linkcolor": "#0080ffaa",
            "source": 9,
            "target": 13
        },
        {
            "linkcolor": "#0080ffaa",
            "source": 9,
            "target": 15
        },
        {
            "linkcolor": "#0080ffaa",
            "source": 9,
            "target": 17
        },
        {
            "linkcolor": "#0080ffaa",
            "source": 9,
            "target": 24
        },
        {
            "linkcolor": "#0080ffaa",
            "source": 10,
            "target": 14
        },
        {
            "linkcolor": "#0080ffaa",
            "source": 10,
            "target": 20
        },
        {
            "linkcolor": "#0080ffaa",
            "source": 10,
            "target": 26
        },
        {
            "linkcolor": "#0080ffaa",
            "source": 10,
            "target": 27
        },
        {
            "linkcolor": "#0080ffaa",
            "source": 10,
            "target": 29
        },
        {
            "linkcolor": "#0080ffaa",
            "source": 11,
            "target": 12
        },
        {
            "linkcolor": "#0080ffaa",
            "source": 11,
            "target": 15
        },
        {
            "linkcolor": "#0080ffaa",
            "source": 11,
            "target": 17
        },
        {
            "linkcolor": "#0080ffaa",
            "source": 11,
            "target": 18
        },
        {
            "linkcolor": "#0080ffaa",
            "source": 11,
            "target": 20
        },
        {
            "linkcolor": "#0080ffaa",
            "source": 11,
            "target": 21
        },
        {
            "linkcolor": "#0080ffaa",
            "source": 11,
            "target": 23
        },
        {
            "linkcolor": "#0080ffaa",
            "source": 11,
            "target": 24
        },
        {
            "linkcolor": "#0080ffaa",
            "source": 11,
            "target": 27
        },
        {
            "linkcolor": "#0080ffaa",
            "source": 12,
            "target": 13
        },
        {
            "linkcolor": "#0080ffaa",
            "source": 12,
            "target": 14
        },
        {
            "linkcolor": "#0080ffaa",
            "source": 12,
            "target": 15
        },
        {
            "linkcolor": "#0080ffaa",
            "source": 12,
            "target": 16
        },
        {
            "linkcolor": "#0080ffaa",
            "source": 12,
            "target": 17
        },
        {
            "linkcolor": "#0080ffaa",
            "source": 12,
            "target": 20
        },
        {
            "linkcolor": "#0080ffaa",
            "source": 12,
            "target": 21
        },
        {
            "linkcolor": "#0080ffaa",
            "source": 12,
            "target": 23
        },
        {
            "linkcolor": "#0080ffaa",
            "source": 12,
            "target": 24
        },
        {
            "linkcolor": "#0080ffaa",
            "source": 12,
            "target": 25
        },
        {
            "linkcolor": "#0080ffaa",
            "source": 12,
            "target": 27
        },
        {
            "linkcolor": "#0080ffaa",
            "source": 13,
            "target": 16
        },
        {
            "linkcolor": "#0080ffaa",
            "source": 13,
            "target": 17
        },
        {
            "linkcolor": "#0080ffaa",
            "source": 13,
            "target": 19
        },
        {
            "linkcolor": "#0080ffaa",
            "source": 13,
            "target": 20
        },
        {
            "linkcolor": "#0080ffaa",
            "source": 13,
            "target": 21
        },
        {
            "linkcolor": "#0080ffaa",
            "source": 13,
            "target": 24
        },
        {
            "linkcolor": "#0080ffaa",
            "source": 13,
            "target": 25
        },
        {
            "linkcolor": "#0080ffaa",
            "source": 14,
            "target": 16
        },
        {
            "linkcolor": "#0080ffaa",
            "source": 14,
            "target": 18
        },
        {
            "linkcolor": "#0080ffaa",
            "source": 14,
            "target": 20
        },
        {
            "linkcolor": "#0080ffaa",
            "source": 14,
            "target": 21
        },
        {
            "linkcolor": "#0080ffaa",
            "source": 14,
            "target": 23
        },
        {
            "linkcolor": "#0080ffaa",
            "source": 14,
            "target": 26
        },
        {
            "linkcolor": "#0080ffaa",
            "source": 14,
            "target": 27
        },
        {
            "linkcolor": "#0080ffaa",
            "source": 15,
            "target": 17
        },
        {
            "linkcolor": "#0080ffaa",
            "source": 15,
            "target": 20
        },
        {
            "linkcolor": "#0080ffaa",
            "source": 15,
            "target": 21
        },
        {
            "linkcolor": "#0080ffaa",
            "source": 15,
            "target": 23
        },
        {
            "linkcolor": "#0080ffaa",
            "source": 15,
            "target": 24
        },
        {
            "linkcolor": "#0080ffaa",
            "source": 16,
            "target": 19
        },
        {
            "linkcolor": "#0080ffaa",
            "source": 16,
            "target": 20
        },
        {
            "linkcolor": "#0080ffaa",
            "source": 16,
            "target": 21
        },
        {
            "linkcolor": "#0080ffaa",
            "source": 16,
            "target": 22
        },
        {
            "linkcolor": "#0080ffaa",
            "source": 16,
            "target": 25
        },
        {
            "linkcolor": "#0080ffaa",
            "source": 16,
            "target": 26
        },
        {
            "linkcolor": "#0080ffaa",
            "source": 16,
            "target": 27
        },
        {
            "linkcolor": "#0080ffaa",
            "source": 16,
            "target": 28
        },
        {
            "linkcolor": "#0080ffaa",
            "source": 17,
            "target": 21
        },
        {
            "linkcolor": "#0080ffaa",
            "source": 17,
            "target": 24
        },
        {
            "linkcolor": "#0080ffaa",
            "source": 18,
            "target": 23
        },
        {
            "linkcolor": "#0080ffaa",
            "source": 18,
            "target": 27
        },
        {
            "linkcolor": "#0080ffaa",
            "source": 19,
            "target": 20
        },
        {
            "linkcolor": "#0080ffaa",
            "source": 19,
            "target": 22
        },
        {
            "linkcolor": "#0080ffaa",
            "source": 19,
            "target": 25
        },
        {
            "linkcolor": "#0080ffaa",
            "source": 19,
            "target": 28
        },
        {
            "linkcolor": "#0080ffaa",
            "source": 20,
            "target": 21
        },
        {
            "linkcolor": "#0080ffaa",
            "source": 20,
            "target": 22
        },
        {
            "linkcolor": "#0080ffaa",
            "source": 20,
            "target": 25
        },
        {
            "linkcolor": "#0080ffaa",
            "source": 20,
            "target": 26
        },
        {
            "linkcolor": "#0080ffaa",
            "source": 20,
            "target": 27
        },
        {
            "linkcolor": "#0080ffaa",
            "source": 20,
            "target": 28
        },
        {
            "linkcolor": "#0080ffaa",
            "source": 21,
            "target": 23
        },
        {
            "linkcolor": "#0080ffaa",
            "source": 21,
            "target": 24
        },
        {
            "linkcolor": "#0080ffaa",
            "source": 21,
            "target": 27
        },
        {
            "linkcolor": "#0080ffaa",
            "source": 22,
            "target": 26
        },
        {
            "linkcolor": "#0080ffaa",
            "source": 22,
            "target": 28
        },
        {
            "linkcolor": "#0080ffaa",
            "source": 22,
            "target": 29
        },
        {
            "linkcolor": "#0080ffaa",
            "source": 23,
            "target": 27
        },
        {
            "linkcolor": "#0080ffaa",
            "source": 25,
            "target": 28
        },
        {
            "linkcolor": "#0080ffaa",
            "source": 26,
            "target": 27
        },
        {
            "linkcolor": "#0080ffaa",
            "source": 26,
            "target": 28
        },
        {
            "linkcolor": "#0080ffaa",
            "source": 26,
            "target": 29
        },
        {
            "linkcolor": "#0080ffaa",
            "source": 28,
            "target": 29
        }
    ]
}